LICENSE
README.md
setup.py
sphinxcontrib_django_urls/__init__.py
sphinxcontrib_django_urls.egg-info/PKG-INFO
sphinxcontrib_django_urls.egg-info/SOURCES.txt
sphinxcontrib_django_urls.egg-info/dependency_links.txt
sphinxcontrib_django_urls.egg-info/not-zip-safe
sphinxcontrib_django_urls.egg-info/top_level.txt