Metadata-Version: 2.1
Name: sphinxcontrib-django-urls
Version: 0.2
Summary: Improve the Sphinx autodoc for Django views by adding urls.
Home-page: https://github.com/mkalioby/sphinxcontrib-django-urls
Download-URL: https://github.com/mkalioby/sphinxcontrib-django-urls/zipball/master
Author: Mohamed ElKalioby
Author-email: mkalioby@mkalioby.com
License: MIT
Classifier: Development Status :: 5 - Production/Stable
Classifier: Environment :: Web Environment
Classifier: Framework :: Django
Classifier: Intended Audience :: Developers
Classifier: License :: OSI Approved :: MIT License
Classifier: Operating System :: OS Independent
Classifier: Programming Language :: Python
Classifier: Programming Language :: Python :: 2.7
Classifier: Programming Language :: Python :: 3
Classifier: Framework :: Django
Classifier: Framework :: Django :: 1.8
Classifier: Framework :: Django :: 2.0
Classifier: Framework :: Django :: 2.1
Classifier: Framework :: Django :: 2.2
Classifier: Topic :: Internet :: WWW/HTTP
Classifier: Topic :: Internet :: WWW/HTTP :: Dynamic Content
Classifier: Topic :: Software Development :: Libraries :: Application Frameworks
Classifier: Topic :: Software Development :: Libraries :: Python Modules
License-File: LICENSE
